maize/__init__.py
maize/command/__init__.py
maize/command/code_generate.py
maize/command/maize_command.py
maize/command/code_template/__init__.py
maize/command/code_template/item_template.py
maize/command/code_template/spider_template.py
maize/common/__init__.py
maize/common/constant/__init__.py
maize/common/constant/command_constant.py
maize/common/constant/request_constant.py
maize/common/constant/setting_constant.py
maize/common/downloader/__init__.py
maize/common/downloader/page_pool.py
maize/common/http/__init__.py
maize/common/http/request.py
maize/common/http/response.py
maize/common/items/__init__.py
maize/common/items/field.py
maize/common/items/items.py
maize/common/model/__init__.py
maize/common/model/base_model.py
maize/common/model/download_response_model.py
maize/common/model/pipeline_model.py
maize/common/model/rpa_model.py
maize/common/model/statistics_model.py
maize/common/model/upload_model.py
maize/core/__init__.py
maize/core/crawler.py
maize/core/decorator_entry.py
maize/core/engine.py
maize/core/processor.py
maize/core/scheduler.py
maize/core/stats_collector.py
maize/core/task_manager.py
maize/downloader/__init__.py
maize/downloader/aiohttp_downloader.py
maize/downloader/httpx_downloader.py
maize/downloader/patchright_downloader.py
maize/downloader/playwright_downloader.py
maize/downloader/base/__init__.py
maize/downloader/base/base_browser_downloader.py
maize/downloader/base/base_downloader.py
maize/exceptions/__init__.py
maize/exceptions/retry_exception.py
maize/exceptions/spider_exception.py
maize/middlewares/__init__.py
maize/middlewares/base_middleware.py
maize/middlewares/middleware_manager.py
maize/middlewares/downloader/__init__.py
maize/middlewares/downloader/default_headers_middleware.py
maize/middlewares/downloader/retry_middleware.py
maize/middlewares/downloader/user_agent_middleware.py
maize/middlewares/pipeline/__init__.py
maize/middlewares/pipeline/cleaner.py
maize/middlewares/pipeline/validation.py
maize-0.4.0.dist-info/METADATA
maize-0.4.0.dist-info/WHEEL
maize-0.4.0.dist-info/entry_points.txt
maize-0.4.0.dist-info/licenses/LICENSE
maize-0.4.0.dist-info/RECORD
